parmscheck/__init__.py
parmscheck/check.py
parmscheck-1.0.7.dist-info/LICENSE
parmscheck-1.0.7.dist-info/METADATA
parmscheck-1.0.7.dist-info/WHEEL
parmscheck-1.0.7.dist-info/top_level.txt
parmscheck-1.0.7.dist-info/RECORD
